CHANGELOG.md
README.md
bambooapi_client/__init__.py
bambooapi_client/client/__init__.py
bambooapi_client/client/activations_api.py
bambooapi_client/client/bambooapi_client.py
bambooapi_client/client/contracts_api.py
bambooapi_client/client/ems_api.py
bambooapi_client/client/events_api.py
bambooapi_client/client/helpers.py
bambooapi_client/client/markets_api.py
bambooapi_client/client/portfolios_api.py
bambooapi_client/client/sites_api.py
bambooapi_client/client/subscriptions_api.py
bambooapi_client/client/users_api.py
bambooapi_client/client/weather_api.py
bambooapi_client/openapi/__init__.py
bambooapi_client/openapi/api/__init__.py
bambooapi_client/openapi/api/activations_api.py
bambooapi_client/openapi/api/admin_api.py
bambooapi_client/openapi/api/clients_api.py
bambooapi_client/openapi/api/contracts_api.py
bambooapi_client/openapi/api/ems_api.py
bambooapi_client/openapi/api/events_api.py
bambooapi_client/openapi/api/flexumers_api.py
bambooapi_client/openapi/api/markets_api.py
bambooapi_client/openapi/api/portfolios_api.py
bambooapi_client/openapi/api/retailers_api.py
bambooapi_client/openapi/api/sites_api.py
bambooapi_client/openapi/api/subscription_api.py
bambooapi_client/openapi/api/users_api.py
bambooapi_client/openapi/api/weather_stations_api.py
bambooapi_client/openapi/api_client.py
bambooapi_client/openapi/apis/__init__.py
bambooapi_client/openapi/configuration.py
bambooapi_client/openapi/exceptions.py
bambooapi_client/openapi/model/__init__.py
bambooapi_client/openapi/model/activation.py
bambooapi_client/openapi/model/activation_create.py
bambooapi_client/openapi/model/activation_data_point.py
bambooapi_client/openapi/model/activation_response_data_point.py
bambooapi_client/openapi/model/activation_status_enum.py
bambooapi_client/openapi/model/activation_update.py
bambooapi_client/openapi/model/alarm_event_create.py
bambooapi_client/openapi/model/algorithm_enum.py
bambooapi_client/openapi/model/app_schemas_ems_profits_data_point.py
bambooapi_client-1.18.7.dist-info/METADATA
bambooapi_client-1.18.7.dist-info/WHEEL
bambooapi_client-1.18.7.dist-info/RECORD
