Metadata-Version: 2.1
Name: bambooapi-client
Version: 1.18.7
Summary: Bamboo Flexibility API
Home-page: https://github.com/bambooenergy/mvp-api-client
License: MIT
Keywords: OpenAPI,OpenAPI-Generator,Bamboo Flexibility API
Author: BambooEnergy
Author-email: development@bambooenergy.tech
Requires-Python: >=3.8,<4.0
Classifier: Development Status :: 4 - Beta
Classifier: License :: OSI Approved :: MIT License
Classifier: Operating System :: OS Independent
Classifier: Programming Language :: Python :: 3
Classifier: Programming Language :: Python :: 3.8
Classifier: Programming Language :: Python :: 3.9
Classifier: Programming Language :: Python :: 3.10
Classifier: Programming Language :: Python :: 3.11
Classifier: Programming Language :: Python :: 3
Classifier: Programming Language :: Python :: 3.8
Classifier: Programming Language :: Python :: 3.9
Requires-Dist: numpy (>=1.21,<1.22)
Requires-Dist: pandas (>=1.4,<1.5)
Requires-Dist: python_dateutil (>=2.8,<2.9)
Requires-Dist: urllib3 (>=1.26,<1.27)
Project-URL: Repository, https://github.com/bambooenergy/mvp-api-client
